koality/__init__.py
koality/checks.py
koality/cli.py
koality/exceptions.py
koality/executor.py
koality/models.py
koality/utils.py
koality-0.7.0.dist-info/WHEEL
koality-0.7.0.dist-info/entry_points.txt
koality-0.7.0.dist-info/METADATA
koality-0.7.0.dist-info/RECORD
