Metadata-Version: 2.3
Name: koality
Version: 0.7.0
Summary: Library for data checks and data quality monitoring based on duckdb.
Keywords: data-quality,data-validation,duckdb,data-checks,data-monitoring,etl,data-pipeline,data-engineering,data-testing,data-profiling,data-observability,sql,analytics,data-warehouse,cli,yaml,pydantic
Author: Team PiT @ Otto Group data.works GmbH, Norbert Maager, Benjamin Gutzmann, Michel Lentzler
Author-email: Benjamin Gutzmann <benjamin.gutzmann@pm.me>
License: # MIT License
Classifier: Development Status :: 4 - Beta
Classifier: Environment :: Console
Classifier: Intended Audience :: Developers
Classifier: Intended Audience :: Science/Research
Classifier: License :: OSI Approved :: MIT License
Classifier: Operating System :: OS Independent
Classifier: Programming Language :: Python
Classifier: Programming Language :: Python :: 3
Classifier: Programming Language :: Python :: 3.12
Classifier: Programming Language :: Python :: 3.13
Classifier: Programming Language :: Python :: 3.14
Classifier: Programming Language :: SQL
Classifier: Topic :: Database
Classifier: Topic :: Scientific/Engineering
Classifier: Topic :: Software Development :: Quality Assurance
Classifier: Topic :: Software Development :: Testing
Classifier: Typing :: Typed
Requires-Dist: click>=8.1.3,<9
Requires-Dist: duckdb>=1.4.2,<2
Requires-Dist: pydantic>=2.12.5,<3
Requires-Dist: pydantic-yaml>=1.6.0,<2
Requires-Dist: pyyaml>=6.0,<7
Requires-Dist: tqdm>=4.67.1,<5
Requires-Python: >=3.12
Project-URL: Documentation, https://ottogroup.github.io/koality/latest/
Project-URL: Issues, https://github.com/ottogroup/koality/issues
Project-URL: Releases, https://github.com/ottogroup/koality/releases
Project-URL: Repository, https://github.com/ottogroup/koality/
